mercury_ml/__init__.py
mercury_ml/common/__init__.py
mercury_ml/common/data_bunch.py
mercury_ml/common/data_set.py
mercury_ml/common/tasks.py
mercury_ml/common/utils.py
mercury_ml/common/artifact_copying/__init__.py
mercury_ml/common/artifact_copying/from_disk.py
mercury_ml/common/artifact_copying/from_gcs.py
mercury_ml/common/artifact_copying/from_hdfs.py
mercury_ml/common/artifact_copying/from_s3.py
mercury_ml/common/artifact_storage/__init__.py
mercury_ml/common/artifact_storage/hdfs.py
mercury_ml/common/artifact_storage/hive.py
mercury_ml/common/artifact_storage/local.py
mercury_ml/common/artifact_storage/mongo.py
mercury_ml/common/data_wrappers/__init__.py
mercury_ml/common/data_wrappers/h2o.py
mercury_ml/common/data_wrappers/keras.py
mercury_ml/common/data_wrappers/numpy.py
mercury_ml/common/data_wrappers/pandas.py
mercury_ml/common/data_wrappers/spark.py
mercury_ml/common/metric_evaluation/__init__.py
mercury_ml/common/metric_evaluation/numpy/__init__.py
mercury_ml/common/metric_evaluation/numpy/label_metrics.py
mercury_ml/common/metric_evaluation/numpy/metrics.py
mercury_ml/common/source_reading/__init__.py
mercury_ml/common/source_reading/disk.py
mercury_ml/common/source_reading/hive.py
mercury_ml/h2o/__init__.py
mercury_ml/h2o/model_evaluation.py
mercury_ml/h2o/model_fitting.py
mercury_ml/h2o/model_loading.py
mercury_ml/h2o/model_saving.py
mercury_ml/h2o/prediction.py
mercury_ml/h2o/session.py
mercury_ml/spark/__init__.py
mercury_ml/spark/session.py
mercury_ml/tensorflow/__init__.py
mercury_ml/tensorflow/containers.py
mercury_ml/tensorflow/custom_loss_functions.py
mercury_ml/tensorflow/generator_preprocessors.py
mercury_ml/tensorflow/loss_function_fetching.py
mercury_ml/tensorflow/model_callbacks.py
mercury_ml/tensorflow/model_compilation.py
mercury_ml/tensorflow/model_evaluation.py
mercury_ml/tensorflow/model_fitting.py
mercury_ml/tensorflow/model_loading.py
mercury_ml/tensorflow/model_saving.py
mercury_ml/tensorflow/optimizer_fetching.py
mercury_ml-0.2.3.dist-info/AUTHORS.md
mercury_ml-0.2.3.dist-info/LICENSE
mercury_ml-0.2.3.dist-info/METADATA
mercury_ml-0.2.3.dist-info/WHEEL
mercury_ml-0.2.3.dist-info/top_level.txt
mercury_ml-0.2.3.dist-info/RECORD
